blue_plugin/README.py
blue_plugin/__init__.py
blue_plugin/__main__.py
blue_plugin/config.env
blue_plugin/env.py
blue_plugin/functions.py
blue_plugin/host.py
blue_plugin/logger.py
blue_plugin/sample.env
blue_plugin/urls.py
blue_plugin/.abcli/abcli.sh
blue_plugin/.abcli/actions.sh
blue_plugin/.abcli/aka.sh
blue_plugin/.abcli/alias.sh
blue_plugin/.abcli/blue_plugin.sh
blue_plugin/.abcli/browse.sh
blue_plugin/.abcli/install.sh
blue_plugin/.abcli/leaf.sh
blue_plugin/.abcli/node.sh
blue_plugin/.abcli/session.sh
blue_plugin/.abcli/node/leaf.sh
blue_plugin/.abcli/tests/README.sh
blue_plugin/.abcli/tests/help.sh
blue_plugin/.abcli/tests/thing.sh
blue_plugin/.abcli/tests/thing_with_args.sh
blue_plugin/.abcli/tests/version.sh
blue_plugin/help/__init__.py
blue_plugin/help/__main__.py
blue_plugin/help/functions.py
blue_plugin/help/node/__init__.py
blue_plugin/help/node/functions.py
blue_plugin/node/__init__.py
blue_plugin/node/__main__.py
blue_plugin/node/functions.py
blue_plugin-3.230.1.dist-info/LICENSE
blue_plugin-3.230.1.dist-info/METADATA
blue_plugin-3.230.1.dist-info/WHEEL
blue_plugin-3.230.1.dist-info/top_level.txt
blue_plugin-3.230.1.dist-info/RECORD
