Metadata-Version: 2.2
Name: blue_plugin
Version: 3.230.1
Summary: 🌀 a git template for an awesome-bash-cli plugin.
Home-page: https://github.com/kamangir/blue-plugin
Author: Arash Abadpour (Kamangir)
Author-email: arash@kamangir.net
License: Public Domain
Classifier: Programming Language :: Python :: 3
Classifier: Programming Language :: Unix Shell
Classifier: License :: Public Domain
Classifier: Operating System :: OS Independent
License-File: LICENSE
Requires-Dist: abcli
Dynamic: author
Dynamic: author-email
Dynamic: classifier
Dynamic: description
Dynamic: description-content-type
Dynamic: home-page
Dynamic: license
Dynamic: requires-dist
Dynamic: summary
